sentr/__init__.py
sentr/cli.py
sentr/apps/__init__.py
sentr/apps/api/.keep
sentr/apps/common/__init__.py
sentr/apps/feature_builder/.env.example
sentr/apps/feature_builder/Dockerfile.loader
sentr/apps/feature_builder/README.md
sentr/apps/feature_builder/__init__.py
sentr/apps/feature_builder/circuit_breaker.py
sentr/apps/feature_builder/config.py
sentr/apps/feature_builder/health.py
sentr/apps/feature_builder/loader.py
sentr/apps/feature_builder/metrics.py
sentr/apps/feature_builder/performance_monitor.py
sentr/apps/feature_builder/redis_utils.py
sentr/apps/feature_builder/service.py
sentr/apps/feature_builder/kafka_consumer/__init__.py
sentr/apps/feature_builder/kafka_consumer/consumer.py
sentr/apps/feature_builder/redis_sink/__init__.py
sentr/apps/feature_builder/redis_sink/pipeline.py
sentr/apps/feature_builder/sliding_window/__init__.py
sentr/apps/feature_builder/sliding_window/edge_window.py
sentr/apps/feature_builder/sliding_window/window.py
sentr/apps/feature_builder/sql/.keep
sentr/apps/feature_builder/sql/windows.sql
sentr/apps/feature_builder/tests/test_configurable_window.py
sentr/apps/feature_builder/tests/test_edge_window.py
sentr/apps/feature_builder/tests/test_edge_window_metrics.py
sentr/apps/feature_builder/tests/test_health_endpoint.py
sentr/apps/feature_builder/tests/test_integration.py
sentr/apps/feature_builder/tests/test_redis_memory_bounds.py
sentr/apps/graph_loader/.keep
sentr/apps/graph_loader/Dockerfile
sentr/apps/graph_loader/README.md
sentr/apps/graph_loader/__init__.py
sentr/apps/graph_loader/config.py
sentr/apps/graph_loader/health_server.py
sentr/apps/graph_loader/main.py
sentr/apps/graph_loader/neo4j_client.py
sentr/apps/graph_loader/poetry.lock
sentr/apps/graph_loader/pyproject.toml
sentr/apps/graph_loader/validate_service.py
sentr/apps/graph_loader/worker.py
sentr/apps/graph_loader/edge_builder/edge_builder.py
sentr/apps/graph_loader/kafka_consumer/consumer.py
sentr/apps/graph_loader/neo4j_writer/neo4j_driver.py
sentr_guard-0.1.4.dist-info/METADATA
sentr_guard-0.1.4.dist-info/WHEEL
sentr_guard-0.1.4.dist-info/entry_points.txt
sentr_guard-0.1.4.dist-info/licenses/LICENSE
sentr_guard-0.1.4.dist-info/RECORD
