Metadata-Version: 2.4
Name: sentr-guard
Version: 0.1.4
Summary: High-performance fraud detection rules engine with sub-millisecond evaluation
Project-URL: Homepage, https://github.com/sentr-dev/sentr-guard
Project-URL: Documentation, https://github.com/sentr-dev/sentr-guard#readme
Project-URL: Repository, https://github.com/sentr-dev/sentr-guard.git
Project-URL: Issues, https://github.com/sentr-dev/sentr-guard/issues
Author-email: Sentr Team <hello@sentr.dev>
License: MIT
License-File: LICENSE
Keywords: detection,engine,fraud,guard,payments,rules,security
Classifier: Development Status :: 4 - Beta
Classifier: Intended Audience :: Developers
Classifier: Intended Audience :: Financial and Insurance Industry
Classifier: License :: OSI Approved :: MIT License
Classifier: Operating System :: OS Independent
Classifier: Programming Language :: Python :: 3
Classifier: Programming Language :: Python :: 3.8
Classifier: Programming Language :: Python :: 3.9
Classifier: Programming Language :: Python :: 3.10
Classifier: Programming Language :: Python :: 3.11
Classifier: Programming Language :: Python :: 3.12
Classifier: Topic :: Office/Business :: Financial
Classifier: Topic :: Security
Classifier: Topic :: Software Development :: Libraries :: Python Modules
Requires-Python: >=3.8
Requires-Dist: pyyaml>=6.0
Requires-Dist: typer>=0.9.0
Provides-Extra: dev
Requires-Dist: black>=24.4.0; extra == 'dev'
Requires-Dist: mypy>=1.10.0; extra == 'dev'
Requires-Dist: pytest-asyncio>=0.26.0; extra == 'dev'
Requires-Dist: pytest-mock>=3.14.0; extra == 'dev'
Requires-Dist: pytest>=8.2.0; extra == 'dev'
Requires-Dist: ruff>=0.4.0; extra == 'dev'
Provides-Extra: full
Requires-Dist: confluent-kafka>=2.4.0; extra == 'full'
Requires-Dist: fastapi>=0.110.0; extra == 'full'
Requires-Dist: numpy>=1.24.0; extra == 'full'
Requires-Dist: orjson>=3.9.0; extra == 'full'
Requires-Dist: prometheus-client>=0.20.0; extra == 'full'
Requires-Dist: pydantic-settings>=2.9.0; extra == 'full'
Requires-Dist: pydantic>=2.7.0; extra == 'full'
Requires-Dist: redis>=5.0.0; extra == 'full'
Requires-Dist: structlog>=23.2.0; extra == 'full'
Requires-Dist: tenacity>=8.2.3; extra == 'full'
Requires-Dist: uvicorn[standard]>=0.29.0; extra == 'full'
